platedet/__init__.py
platedet/cli.py
platedet/platedet.py
platedet/artifacts/platedet.onnx
platedet-0.0.2.dist-info/METADATA
platedet-0.0.2.dist-info/WHEEL
platedet-0.0.2.dist-info/entry_points.txt
platedet-0.0.2.dist-info/top_level.txt
platedet-0.0.2.dist-info/RECORD
