Metadata-Version: 2.1
Name: platedet
Version: 0.0.2
Summary: Detect license plates
Home-page: https://github.com/pstwh/platedet
Keywords: plate,detection,brazilian
Requires-Python: >=3.5, <4
Requires-Dist: pillow ==10.4.0
Requires-Dist: opencv-python-headless ==4.10.0.84
Provides-Extra: cpu
Requires-Dist: onnxruntime ==1.18.1 ; extra == 'cpu'
Provides-Extra: gpu
Requires-Dist: onnxruntime-gpu ==1.18.1 ; extra == 'gpu'
